indonesia_holiday/__init__.py
indonesia_holiday/holiday.py
indonesia_holiday-1.0.dist-info/METADATA
indonesia_holiday-1.0.dist-info/WHEEL
indonesia_holiday-1.0.dist-info/top_level.txt
indonesia_holiday-1.0.dist-info/RECORD
